{
    "span_0": "\u00d7",
    "span_34": "Dermatology",
    "h1_38": "HCA Florida Orange Park Hospital Program",
    "h3_39": "HCA Florida Orange Park Hospital",
    "label_41": "Phone",
    "span_42": "(904) 369-2026",
    "label_43": "Website",
    "span_44": "https://orangeparkmedical.com/physicians/graduate-medical-education/dermatology/",
    "label_46": "Compare Program",
    "label_47": "Address",
    "span_48": "2001 Kingsley Ave",
    "span_49": "GME Suite",
    "span_50": "Orange Park, FL 32073",
    "label_51": "Email",
    "label_52": "Region",
    "span_53": "South Atlantic",
    "label_54": "ACGME Program Code",
    "span_55": "0801100140",
    "label_56": "Program Director",
    "span_57": "Karthik Krishnamurthy",
    "label_58": "Program Coordinator",
    "span_59": "Leah Todd",
    "label_60": "Program Coordinator Phone",
    "span_61": "(904) 639-2026",
    "p_63": "Dashes (\"-\") indicate data for a particular field are not provided for this program in Residency Explorer. Reasons why data are not being provided can vary (e.g., they are not reported or available, they are not applicable, or they are based on an insufficient number of people for reporting purposes).",
    "h2_64": "Program Quick Facts",
    "h3_67": "# of Filled Resident Positions, by Year*",
    "th_68": "Program Year",
    "th_69": "#",
    "th_70": "Total",
    "td_71": "9",
    "th_72": "PGY1",
    "td_73": "3",
    "th_74": "PGY2",
    "td_75": "3",
    "th_76": "PGY3",
    "td_77": "3",
    "p_78": "*Totals may vary from year to year due to off-cycle residents.",
    "h3_79": "Program Characteristics",
    "th_80": "Characteristics",
    "th_82": "Institutional Setting",
    "td_83": "Affiliated Hospital",
    "th_84": "Participates in ERAS",
    "td_85": "Yes",
    "th_86": "Participates in NRMP Main Match",
    "td_87": "Yes",
    "th_88": "Accreditation Status",
    "td_89": "Continued Accreditation",
    "th_90": "Accreditation Effective Date",
    "td_91": "1/6/2023",
    "th_92": "Accredited Length of Training (years)",
    "td_93": "3",
    "th_94": "Program has Osteopathic Recognition",
    "td_95": "No",
    "th_96": "# of Residents Who Were Graduates of a Joint MD-PhD program",
    "td_97": "\u2013",
    "h2_98": "Application & Match Trends",
    "h3_101": "Application Trends",
    "h3_102": "2023 Match Outcomes",
    "th_103": "Categorical",
    "th_104": "# of Positions Offered:",
    "td_105": "\u2013",
    "span_106": "\u2013",
    "th_107": "# of Positions Filled:",
    "td_108": "\u2013",
    "span_109": "\u2013",
    "th_110": "Advanced",
    "th_111": "# of Positions Offered:",
    "td_112": "3",
    "th_113": "# of Positions Filled:",
    "td_114": "3",
    "h3_115": "2022 Program Selectivity",
    "th_117": "This Program",
    "th_118": "Average for ACGME\nDermatology Programs",
    "th_119": "# of Positions Offered in the\nNRMP Main Residency Match:",
    "td_120": "3",
    "td_121": "4",
    "th_122": "# of Applicants:",
    "td_123": "446",
    "td_124": "542",
    "th_125": "% of Applicants\nInterviewed:",
    "td_126": "9.0",
    "td_127": "7.5",
    "h2_128": "Program Signal and Geographic Preference Data for the Program\u2019s Specialty",
    "h3_131": "Distribution of Program Interview Invitation Rates by Signal Status for the 2023 Cycle : Dermatology (n= 68 programs)",
    "h3_133": "Distribution of Program Interview Invitation Rates by Geographic Preference for the 2023 Cycle : Dermatology (n= 86 programs)",
    "h2_137": "Applicant Information",
    "h3_140": "Score Requirements",
    "th_141": "USMLE Score Requirements",
    "th_142": "Step 1 Required for Interview Consideration",
    "td_143": "Yes",
    "th_145": "Passing Step 1 Required for Interview Consideration",
    "td_146": "\u2013",
    "span_147": "\u2013",
    "th_148": "Minimum Step 1 Score for Interview Consideration",
    "td_149": "240",
    "th_150": "Step 2 Required for Interview Consideration",
    "td_151": "Yes",
    "th_153": "Passing Step 2 Required for Interview Consideration",
    "td_154": "\u2013",
    "span_155": "\u2013",
    "th_156": "Minimum Step 2 Score for Interview Consideration",
    "td_157": "240",
    "th_158": "COMLEX - USA Score Requirements",
    "th_159": "Level 1 Required for Interview Consideration",
    "td_160": "Yes",
    "th_162": "Passing Level 1 Required for Interview Consideration",
    "td_163": "\u2013",
    "span_164": "\u2013",
    "th_165": "Minimum Level 1 Score for Interview Consideration",
    "td_166": "600",
    "th_167": "Level 2 Required for Interview Consideration",
    "td_168": "Yes",
    "th_170": "Passing Level 2 Required for Interview Consideration",
    "td_171": "\u2013",
    "span_172": "\u2013",
    "th_173": "Minimum Level 2 Score for Interview Consideration",
    "td_174": "600",
    "h3_175": "More Information",
    "th_176": "Visa Status Information\nThis program will consider an appropriately qualified applicant with the following visa or visa status:",
    "p_177": "This program will consider an appropriately qualified applicant with the following visa or visa status:",
    "th_178": "J-1 Sponsorship through ECFMG",
    "td_179": "No",
    "th_180": "H1-B",
    "td_181": "No",
    "th_182": "F-1 (OPT Program)",
    "td_183": "No",
    "th_184": "Other Information",
    "th_185": "# of required letters of recommendation",
    "td_186": "3",
    "th_187": "Interviews available via web conferencing*",
    "td_188": "Yes",
    "p_190": "*Response reported prior to the COVID-19 pandemic. Please check the program website for more information.",
    "h3_191": "Honor Society Membership",
    "p_192": "Percentage of matched applicants to program with the given membership",
    "th_193": "Membership",
    "th_194": "This Program",
    "th_195": "This Specialty",
    "th_196": "Alpha Omega Alpha (AOA)",
    "td_197": "11%",
    "td_198": "39%",
    "th_199": "Gold Humanism Honor Society (GHHS)",
    "td_200": "17%",
    "td_201": "14%",
    "th_202": "Sigma Sigma Phi (SSP)",
    "td_203": "22%",
    "td_204": "4%",
    "h2_205": "Resident Salary and Benefits",
    "h3_208": "Resident Salary and Leave, By Year",
    "th_209": "Program Year",
    "th_210": "Salary",
    "th_211": "# of Paid Sick Days",
    "th_212": "# of Paid Vacation Days",
    "th_213": "PGY1",
    "td_214": "\u2013",
    "span_215": "\u2013",
    "td_216": "\u2013",
    "span_217": "\u2013",
    "td_218": "\u2013",
    "span_219": "\u2013",
    "th_220": "PGY2",
    "td_221": "\u2013",
    "span_222": "\u2013",
    "td_223": "\u2013",
    "span_224": "\u2013",
    "td_225": "\u2013",
    "span_226": "\u2013",
    "th_227": "PGY3",
    "td_228": "\u2013",
    "span_229": "\u2013",
    "td_230": "\u2013",
    "span_231": "\u2013",
    "td_232": "\u2013",
    "span_233": "\u2013",
    "h3_234": "Program Employment Benefits",
    "th_235": "Benefit Offered to Residents",
    "th_236": "Part-time/shared schedule positions",
    "td_237": "\u2013",
    "span_238": "\u2013",
    "th_239": "On-site child care",
    "td_240": "\u2013",
    "span_241": "\u2013",
    "th_242": "Subsidized child care",
    "td_243": "\u2013",
    "span_244": "\u2013",
    "th_245": "Moving allowance",
    "td_246": "\u2013",
    "span_247": "\u2013",
    "th_248": "Housing stipend",
    "td_249": "\u2013",
    "span_250": "\u2013",
    "th_251": "Free parking",
    "td_252": "Yes",
    "th_254": "On-call meal allowance",
    "td_255": "Yes",
    "th_257": "Tablets/technology allowance",
    "td_258": "Yes",
    "th_260": "Placement assistance upon program completion",
    "td_261": "\u2013",
    "span_262": "\u2013",
    "th_263": "Average # of days off per week in Year 1",
    "td_264": "2",
    "th_265": "Maximum # of paid days for family/medical leave",
    "td_266": "21",
    "th_267": "Maximum # of unpaid days for family/medical leave",
    "td_268": "Negotiable",
    "h2_269": "Resident Practice and Educational Environment",
    "h3_272": "Practice Environment",
    "th_273": "Average hours per week in Year 1 that residents work",
    "td_274": "45 hrs.",
    "th_275": "Maximum consecutive hours resident is allowed to work in Year 1",
    "td_276": "12 hrs.",
    "th_277": "Program allows residents/fellows beyond PGY1 to moonlight",
    "td_278": "No",
    "th_279": "Percentage of training spent by residents/fellows in Year 1 in hospital outpatient clinics in all teaching hospitals used",
    "td_280": "0%",
    "th_281": "Percentage of training spent by residents/fellows in Year 1 in ambulatory nonhospital community-based settings not attached to any hospital",
    "td_282": "80%",
    "h3_283": "Education and Research Environment",
    "th_284": "Dedicated research rotation",
    "td_285": "Optional",
    "th_286": "# of weeks in required research rotation",
    "td_287": "\u2013",
    "th_288": "Average hours per week in Year 1 that residents/fellow are expected to attend regularly scheduled lectures/conferences",
    "td_289": "8",
    "h2_290": "Educational and Research Opportunities",
    "h3_293": "Educational Benefits",
    "th_294": "Integrative medicine curriculum",
    "td_295": "\u2013",
    "th_296": "Formal mentoring program",
    "td_297": "\u2013",
    "th_298": "Formal program to assist residents/fellows in developing teaching skills",
    "td_299": "\u2013",
    "th_300": "Formal program to foster interprofessional teamwork",
    "td_301": "\u2013",
    "th_302": "Instruction in medical Spanish or other non-English language",
    "td_303": "\u2013",
    "th_304": "Alternative/complementary medicine curriculum",
    "td_305": "\u2013",
    "th_306": "Economics of health care systems curriculum",
    "td_307": "\u2013",
    "th_308": "Debt management and financial counseling",
    "td_309": "\u2013",
    "th_310": "International experience/global health",
    "td_311": "\u2013",
    "th_312": "Resident/fellow retreats",
    "td_313": "\u2013",
    "th_314": "Hospice/home care experience",
    "td_315": "\u2013",
    "th_316": "MPH, MBA, PhD or other advanced degree training",
    "td_317": "\u2013",
    "th_318": "Academic support for USMLE Step 3 prep",
    "td_319": "\u2013",
    "th_320": "Health systems leadership skills curriculum",
    "td_321": "\u2013",
    "h3_322": "Special Tracks",
    "th_323": "Hospitalist",
    "td_324": "\u2013",
    "th_325": "Primary Care",
    "td_326": "\u2013",
    "th_327": "Non-accredited research track/fellowship",
    "td_328": "\u2013",
    "th_329": "Rural",
    "td_330": "\u2013",
    "th_331": "Women's Health",
    "td_332": "\u2013",
    "h2_333": "Resident Demographics and Background, All Training Years",
    "h3_336": "Percentage of Residents by Race/Ethnicity",
    "span_337": "Data Not Available",
    "p_338": "The race/ethnicity data are shown alone or in combination with other race/ethnicity responses. Because some individuals may report multiple races/ethnicities, the totals may not equal 100%. Only residents who are U.S. citizens or permanent residents are included in race/ethnicity counts.",
    "h3_339": "Percentage of Residents by Gender",
    "h3_340": "Gender",
    "span_341": "Data Not Available",
    "h3_342": "Percentage of Residents by Medical Student Type",
    "h3_343": "Medical Student Type",
    "span_344": "Data Not Available",
    "h2_345": "Resident Medical School Background",
    "span_348": "Data Not Available",
    "h2_354": "Resident Career Plans",
    "h3_357": "Graduates of the Residency Program",
    "p_361": "The views expressed herein are those of the authors and do not necessarily reflect the position or policy of the organizations contributing such data.\nAll logos and trademarks appearing in the resource are the property of their respective owners.",
    "p_362": "\u00a9 2024 AAMC | 655 K Street, NW, Suite 100, Washington, DC, 20001-2399",
    "p_363": "Website Terms and Conditions | Privacy Statement",
    "p_364": "P2023-13412 -b5e9",
    "span_365": "-b5e9"
}